{"textures":{"0":"modelengine:entity/item_press"},"elements":[{"name":"cube","from":[8.0,19.95,7.4],"to":[8.9,20.850002,8.3],"rotation":{"angle":0.0,"axis":"x","origin":[8.0,19.95,7.4]},"faces":{"down":{"uv":[5.0,5.5,4.875,5.625],"rotation":0,"texture":"#0","tintindex":0},"east":{"uv":[1.875,5.25,2.0,5.375],"rotation":0,"texture":"#0","tintindex":0},"north":{"uv":[1.875,5.125,2.0,5.25],"rotation":0,"texture":"#0","tintindex":0},"south":{"uv":[4.0,5.25,4.125,5.375],"rotation":0,"texture":"#0","tintindex":0},"up":{"uv":[5.0,5.5,4.875,5.375],"rotation":0,"texture":"#0","tintindex":0},"west":{"uv":[4.125,5.25,4.25,5.375],"rotation":0,"texture":"#0","tintindex":0}}}],"display":{"head":{"translation":[0.0,-6.4,0.0],"rotation":[0.0,0.0,0.0],"scale":[3.8095,3.8095,3.8095]}}}