{"credit":"MadewithBlockbench","texture_size":[24,24],"textures":{"0":"gamula/cosmetics/hats/magic_hat","particle":"gamula/cosmetics/hats/magic_hat"},"elements":[{"from":[4.5,5.31693,4.5],"to":[11.5,5.81693,11.5],"rotation":{"angle":0,"axis":"y","origin":[8,5.81693,8]},"faces":{"north":{"uv":[10.16667,0,14.83333,0.33333],"texture":"#0"},"east":{"uv":[10.16667,0,14.83333,0.33333],"texture":"#0"},"south":{"uv":[10.16667,0,14.83333,0.33333],"texture":"#0"},"west":{"uv":[10.16667,0,14.83333,0.33333],"texture":"#0"},"up":{"uv":[4.66667,4.66667,0,0],"texture":"#0"},"down":{"uv":[4.66667,0,0,4.66667],"texture":"#0"}}},{"from":[6.08,5.76653,6.07821],"to":[9.92,8.32653,9.91821],"rotation":{"angle":0,"axis":"y","origin":[1.6,-3.83347,1.59821]},"faces":{"north":{"uv":[4.66667,5.33333,7.16667,7],"texture":"#0"},"east":{"uv":[7.33333,0,9.83333,1.66667],"texture":"#0"},"south":{"uv":[7.33333,2,9.83333,3.66667],"texture":"#0"},"west":{"uv":[7.33333,4,9.83333,5.66667],"texture":"#0"},"up":{"uv":[7.16667,2.5,4.66667,0],"texture":"#0"}}},{"from":[6.4,7.6168,6.63825],"to":[9.6,10.1768,9.83825],"rotation":{"angle":22.5,"axis":"x","origin":[8,8.8968,8.23825]},"faces":{"north":{"uv":[4.66667,7.33333,6.83333,9],"texture":"#0"},"east":{"uv":[4.66667,7.33333,6.83333,9],"texture":"#0"},"south":{"uv":[4.66667,7.33333,6.83333,9],"texture":"#0"},"west":{"uv":[4.66667,7.33333,6.83333,9],"texture":"#0"},"up":{"uv":[6.83333,4.83333,4.66667,2.66667],"texture":"#0"}}},{"from":[6.72,8.59093,7.64228],"to":[9.28,11.15093,10.20228],"rotation":{"angle":-22.5,"axis":"x","origin":[8,9.99893,8.92228]},"faces":{"east":{"uv":[10,2,11.66667,3.66667],"rotation":270,"texture":"#0"},"south":{"uv":[4.66667,9.33333,6.33333,11],"texture":"#0"},"west":{"uv":[10,2,11.66667,3.66667],"rotation":90,"texture":"#0"},"up":{"uv":[11.66667,3.66667,10,2],"texture":"#0"},"down":{"uv":[11.66667,2,10,3.66667],"texture":"#0"}}},{"from":[7.36,9.26743,11.39654],"to":[8.64,10.54743,13.95654],"rotation":{"angle":45,"axis":"x","origin":[8,10.03543,12.67654]},"faces":{"east":{"uv":[11.33333,10.33333,12.16667,8.66667],"rotation":90,"texture":"#0"},"south":{"uv":[11.33333,11.33333,12.16667,12.16667],"texture":"#0"},"west":{"uv":[11.33333,8.66667,12.16667,10.33333],"rotation":90,"texture":"#0"},"up":{"uv":[12.16667,10.33333,11.33333,8.66667],"texture":"#0"},"down":{"uv":[12.16667,8.66667,11.33333,10.33333],"texture":"#0"}}},{"from":[7.04,9.47307,9.66399],"to":[8.96,11.39307,12.22399],"rotation":{"angle":0,"axis":"x","origin":[8,10.40107,8.38399]},"faces":{"east":{"uv":[10,9,11.33333,7.33333],"rotation":90,"texture":"#0"},"south":{"uv":[10,9.33333,11.33333,10.66667],"texture":"#0"},"west":{"uv":[10,7.33333,11.33333,9],"rotation":90,"texture":"#0"},"up":{"uv":[11.33333,9,10,7.33333],"texture":"#0"},"down":{"uv":[11.33333,7.33333,10,9],"texture":"#0"}}}],"gui_light":"front","display":{"thirdperson_righthand":{"rotation":[41,0,0],"translation":[0,2.25,0]},"thirdperson_lefthand":{"rotation":[41,0,0],"translation":[0,2.25,0]},"firstperson_righthand":{"rotation":[0,106,0],"translation":[-2.5,4.75,1.5],"scale":[1.17773,1.17773,1.17773]},"firstperson_lefthand":{"rotation":[0,106,0],"translation":[-2.5,4.75,1.5],"scale":[1.17773,1.17773,1.17773]},"ground":{"translation":[0,2.5,0],"scale":[1.77734,1.77734,1.77734]},"gui":{"rotation":[33,135,0],"scale":[1.59571,1.59571,1.59571]},"head":{"rotation":[10,0,0],"translation":[0,10,1.25],"scale":[4,4,4]},"fixed":{"rotation":[-90,0,0],"translation":[0,0,-10.5],"scale":[3.8418,3.8418,3.8418]}}}