{"textures":{"0":"modelengine:entity/mso_lobster2"},"elements":[{"name":"cube","from":[6.8,7.1,2.4499998],"to":[9.2,9.5,9.05],"rotation":{"angle":0.0,"axis":"x","origin":[8.6,7.4,0.9499998]},"faces":{"down":{"uv":[3.5,6.5,2.5,9.25],"rotation":0,"texture":"#0","tintindex":0},"east":{"uv":[4.0,2.25,6.75,3.25],"rotation":0,"texture":"#0","tintindex":0},"north":{"uv":[5.5,4.25,6.5,5.25],"rotation":0,"texture":"#0","tintindex":0},"south":{"uv":[8.75,2.0,9.75,3.0],"rotation":0,"texture":"#0","tintindex":0},"up":{"uv":[2.5,9.25,1.5,6.5],"rotation":0,"texture":"#0","tintindex":0},"west":{"uv":[5.5,0.0,8.25,1.0],"rotation":0,"texture":"#0","tintindex":0}}},{"name":"cube","from":[4.7,7.7,7.85],"to":[11.3,7.7,12.650001],"rotation":{"angle":0.0,"axis":"x","origin":[6.5,7.4,0.9499998]},"faces":{"down":{"uv":[2.75,3.25,0.0,5.25],"rotation":0,"texture":"#0","tintindex":0},"east":{"uv":[0.0,0.0,2.0,0.0],"rotation":0,"texture":"#0","tintindex":0},"north":{"uv":[0.0,0.0,2.75,0.0],"rotation":0,"texture":"#0","tintindex":0},"south":{"uv":[0.0,0.0,2.75,0.0],"rotation":0,"texture":"#0","tintindex":0},"up":{"uv":[2.75,5.25,0.0,3.25],"rotation":0,"texture":"#0","tintindex":0},"west":{"uv":[0.0,0.0,2.0,0.0],"rotation":0,"texture":"#0","tintindex":0}}}],"display":{"head":{"translation":[0.0,-6.4,0.0],"rotation":[0.0,0.0,0.0],"scale":[3.8095,3.8095,3.8095]}}}
