{"textures":{"0":"modelengine:entity/npc_piranha"},"elements":[{"from":[9.928572,24.542858,-12.285715],"to":[10.5,25.257145,-12.285715],"rotation":{"angle":45.0,"axis":"x","origin":[8.571428,25.0,-12.57143]},"faces":{"north":{"uv":[13.125,13.5,12.5,14.25],"rotation":0,"texture":"#0","tintindex":0}}},{"from":[12.5,24.353054,-12.801727],"to":[13.071428,25.067339,-12.801727],"rotation":{"angle":-45.0,"axis":"z","origin":[10.285714,24.710196,-12.658871]},"faces":{"north":{"uv":[13.125,13.5,12.5,14.25],"rotation":0,"texture":"#0","tintindex":0}}},{"from":[11.357143,24.353054,-12.801727],"to":[11.928572,25.067339,-12.801727],"rotation":{"angle":-45.0,"axis":"z","origin":[10.285714,24.710196,-12.658871]},"faces":{"north":{"uv":[13.125,13.5,12.5,14.25],"rotation":0,"texture":"#0","tintindex":0}}},{"from":[4.0714283,24.353054,-12.801727],"to":[4.642857,25.067339,-12.801727],"rotation":{"angle":45.0,"axis":"z","origin":[5.714286,24.710196,-12.658871]},"faces":{"north":{"uv":[12.5,13.5,13.125,14.25],"rotation":0,"texture":"#0","tintindex":0}}},{"from":[2.9285712,24.353054,-12.801727],"to":[3.5,25.067339,-12.801727],"rotation":{"angle":45.0,"axis":"z","origin":[5.714286,24.710196,-12.658871]},"faces":{"north":{"uv":[12.5,13.5,13.125,14.25],"rotation":0,"texture":"#0","tintindex":0}}},{"from":[8.928572,24.542858,-12.285715],"to":[9.5,25.257145,-12.285715],"rotation":{"angle":45.0,"axis":"x","origin":[8.571428,25.0,-12.57143]},"faces":{"north":{"uv":[13.125,13.5,12.5,14.25],"rotation":0,"texture":"#0","tintindex":0}}},{"from":[6.5714283,24.542858,-12.285715],"to":[7.142857,25.257145,-12.285715],"rotation":{"angle":45.0,"axis":"x","origin":[8.571428,25.0,-12.57143]},"faces":{"north":{"uv":[13.125,13.5,12.5,14.25],"rotation":0,"texture":"#0","tintindex":0}}},{"from":[7.714286,24.542858,-12.285715],"to":[8.285714,25.257145,-12.285715],"rotation":{"angle":45.0,"axis":"x","origin":[8.571428,25.0,-12.57143]},"faces":{"north":{"uv":[13.125,13.5,12.5,14.25],"rotation":0,"texture":"#0","tintindex":0}}},{"from":[5.5,24.542858,-12.285715],"to":[6.0714283,25.257145,-12.285715],"rotation":{"angle":45.0,"axis":"x","origin":[8.571428,25.0,-12.57143]},"faces":{"north":{"uv":[13.125,13.5,12.5,14.25],"rotation":0,"texture":"#0","tintindex":0}}}],"display":{"head":{"translation":[0.0,-6.4,0.0],"scale":[4.0,4.0,4.0]}}}