{
	"credit": "Made with Blockbench",
	"texture_size": [128, 128],
	"textures": {
		"0": "gamula/furniture/arcade/18_crazy_frog_hammer_texture",
		"particle": "gamula/furniture/arcade/18_crazy_frog_hammer_texture"
	},
	"elements": [
		{
			"from": [0, 0, 0],
			"to": [16, 10, 23],
			"rotation": {"angle": 0, "axis": "y", "origin": [8, 15.25, 12.25]},
			"faces": {
				"north": {"uv": [5.5, 4.125, 7.5, 5.375], "texture": "#0"},
				"east": {"uv": [2.875, 2.875, 0, 4.125], "texture": "#0"},
				"south": {"uv": [8.4375, 5.0625, 10.4375, 6.3125], "texture": "#0"},
				"west": {"uv": [2.875, 2.875, 5.75, 4.125], "texture": "#0"},
				"up": {"uv": [2, 2.875, 0, 0], "texture": "#0"},
				"down": {"uv": [4, 0, 2, 2.875], "texture": "#0"}
			}
		},
		{
			"from": [11, 10, 1],
			"to": [14, 11, 4],
			"rotation": {"angle": 0, "axis": "y", "origin": [8, 15.25, 12.25]},
			"faces": {
				"north": {"uv": [7.875, 4.375, 8.25, 4.5], "texture": "#0"},
				"east": {"uv": [7.875, 4.375, 8.25, 4.5], "texture": "#0"},
				"south": {"uv": [7.875, 4.375, 8.25, 4.5], "texture": "#0"},
				"west": {"uv": [7.875, 4.375, 8.25, 4.5], "texture": "#0"},
				"up": {"uv": [8, 1.125, 7.625, 0.75], "texture": "#0"},
				"down": {"uv": [8, 1.125, 7.625, 1.5], "texture": "#0"}
			}
		},
		{
			"from": [6.5, 10, 1],
			"to": [9.5, 11, 4],
			"rotation": {"angle": 0, "axis": "y", "origin": [8, 15.25, 12.25]},
			"faces": {
				"north": {"uv": [7.875, 4.375, 8.25, 4.5], "texture": "#0"},
				"east": {"uv": [7.875, 4.375, 8.25, 4.5], "texture": "#0"},
				"south": {"uv": [7.875, 4.375, 8.25, 4.5], "texture": "#0"},
				"west": {"uv": [7.875, 4.375, 8.25, 4.5], "texture": "#0"},
				"up": {"uv": [8, 1.125, 7.625, 0.75], "texture": "#0"},
				"down": {"uv": [8, 1.125, 7.625, 1.5], "texture": "#0"}
			}
		},
		{
			"from": [2, 10, 1],
			"to": [5, 11, 4],
			"rotation": {"angle": 0, "axis": "y", "origin": [8, 15.25, 12.25]},
			"faces": {
				"north": {"uv": [7.875, 4.375, 8.25, 4.5], "texture": "#0"},
				"east": {"uv": [7.875, 4.375, 8.25, 4.5], "texture": "#0"},
				"south": {"uv": [7.875, 4.375, 8.25, 4.5], "texture": "#0"},
				"west": {"uv": [7.875, 4.375, 8.25, 4.5], "texture": "#0"},
				"up": {"uv": [8, 1.125, 7.625, 0.75], "texture": "#0"},
				"down": {"uv": [8, 1.125, 7.625, 1.5], "texture": "#0"}
			}
		},
		{
			"from": [4, 10, 5.5],
			"to": [7, 11, 8.5],
			"rotation": {"angle": 0, "axis": "y", "origin": [8, 15.25, 12.25]},
			"faces": {
				"north": {"uv": [7.875, 4.375, 8.25, 4.5], "texture": "#0"},
				"east": {"uv": [7.875, 4.375, 8.25, 4.5], "texture": "#0"},
				"south": {"uv": [7.875, 4.375, 8.25, 4.5], "texture": "#0"},
				"west": {"uv": [7.875, 4.375, 8.25, 4.5], "texture": "#0"},
				"up": {"uv": [8, 1.125, 7.625, 0.75], "texture": "#0"},
				"down": {"uv": [8, 1.125, 7.625, 1.5], "texture": "#0"}
			}
		},
		{
			"from": [9, 10, 5.5],
			"to": [12, 11, 8.5],
			"rotation": {"angle": 0, "axis": "y", "origin": [8, 15.25, 12.25]},
			"faces": {
				"north": {"uv": [7.875, 4.375, 8.25, 4.5], "texture": "#0"},
				"east": {"uv": [7.875, 4.375, 8.25, 4.5], "texture": "#0"},
				"south": {"uv": [7.875, 4.375, 8.25, 4.5], "texture": "#0"},
				"west": {"uv": [7.875, 4.375, 8.25, 4.5], "texture": "#0"},
				"up": {"uv": [8, 1.125, 7.625, 0.75], "texture": "#0"},
				"down": {"uv": [8, 1.125, 7.625, 1.5], "texture": "#0"}
			}
		},
		{
			"from": [2, 10, 10],
			"to": [5, 11, 13],
			"rotation": {"angle": 0, "axis": "y", "origin": [8, 15.25, 12.25]},
			"faces": {
				"north": {"uv": [7.875, 4.375, 8.25, 4.5], "texture": "#0"},
				"east": {"uv": [7.875, 4.375, 8.25, 4.5], "texture": "#0"},
				"south": {"uv": [7.875, 4.375, 8.25, 4.5], "texture": "#0"},
				"west": {"uv": [7.875, 4.375, 8.25, 4.5], "texture": "#0"},
				"up": {"uv": [8, 1.125, 7.625, 0.75], "texture": "#0"},
				"down": {"uv": [8, 1.125, 7.625, 1.5], "texture": "#0"}
			}
		},
		{
			"from": [6.5, 10, 10],
			"to": [9.5, 11, 13],
			"rotation": {"angle": 0, "axis": "y", "origin": [8, 15.25, 12.25]},
			"faces": {
				"north": {"uv": [7.875, 4.375, 8.25, 4.5], "texture": "#0"},
				"east": {"uv": [7.875, 4.375, 8.25, 4.5], "texture": "#0"},
				"south": {"uv": [7.875, 4.375, 8.25, 4.5], "texture": "#0"},
				"west": {"uv": [7.875, 4.375, 8.25, 4.5], "texture": "#0"},
				"up": {"uv": [8, 1.125, 7.625, 0.75], "texture": "#0"},
				"down": {"uv": [8, 1.125, 7.625, 1.5], "texture": "#0"}
			}
		},
		{
			"from": [11, 10, 10],
			"to": [14, 11, 13],
			"rotation": {"angle": 0, "axis": "y", "origin": [8, 15.25, 12.25]},
			"faces": {
				"north": {"uv": [7.875, 4.375, 8.25, 4.5], "texture": "#0"},
				"east": {"uv": [7.875, 4.375, 8.25, 4.5], "texture": "#0"},
				"south": {"uv": [7.875, 4.375, 8.25, 4.5], "texture": "#0"},
				"west": {"uv": [7.875, 4.375, 8.25, 4.5], "texture": "#0"},
				"up": {"uv": [8, 1.125, 7.625, 0.75], "texture": "#0"},
				"down": {"uv": [8, 1.125, 7.625, 1.5], "texture": "#0"}
			}
		},
		{
			"from": [0, 10, 14],
			"to": [16, 11, 23],
			"rotation": {"angle": 0, "axis": "y", "origin": [8, 15.25, 12.25]},
			"faces": {
				"north": {"uv": [6, 2.75, 8, 2.875], "texture": "#0"},
				"east": {"uv": [7.5, 6.375, 8.625, 6.5], "texture": "#0"},
				"south": {"uv": [6.875, 1.625, 8.875, 1.75], "texture": "#0"},
				"west": {"uv": [7.5, 6.375, 8.625, 6.5], "texture": "#0"},
				"up": {"uv": [6, 2.875, 4, 1.75], "texture": "#0"},
				"down": {"uv": [7.75, 2.875, 5.75, 4], "texture": "#0"}
			}
		},
		{
			"from": [15, 11, 14],
			"to": [16, 25, 21],
			"rotation": {"angle": 0, "axis": "y", "origin": [8, 15.25, 12.25]},
			"faces": {
				"north": {"uv": [2.625, 7.25, 2.75, 9], "texture": "#0"},
				"east": {"uv": [6.625, 6.625, 5.75, 8.375], "texture": "#0"},
				"south": {"uv": [6.625, 7.5, 6.75, 9.25], "texture": "#0"},
				"west": {"uv": [5.75, 6.625, 4.875, 8.375], "texture": "#0"},
				"up": {"uv": [4.875, 8.5, 4.75, 7.625], "texture": "#0"},
				"down": {"uv": [7.875, 7.25, 7.75, 8.125], "texture": "#0"}
			}
		},
		{
			"from": [0, 11, 21],
			"to": [16, 25, 23],
			"rotation": {"angle": 0, "axis": "y", "origin": [8, 15.25, 12.25]},
			"faces": {
				"north": {"uv": [4, 0, 6, 1.75], "texture": "#0"},
				"east": {"uv": [4, 7, 3.75, 8.75], "texture": "#0"},
				"south": {"uv": [0, 4.125, 2, 5.875], "texture": "#0"},
				"west": {"uv": [3.75, 7, 4, 8.75], "texture": "#0"},
				"up": {"uv": [8, 2.75, 6, 2.5], "texture": "#0"},
				"down": {"uv": [2.75, 7, 0.75, 7.25], "texture": "#0"}
			}
		},
		{
			"from": [0, 25, 14],
			"to": [16, 26, 23],
			"rotation": {"angle": 0, "axis": "y", "origin": [8, 15.25, 12.25]},
			"faces": {
				"north": {"uv": [7.5, 4.75, 9.5, 4.875], "texture": "#0"},
				"east": {"uv": [7.625, 1.5, 8.75, 1.625], "texture": "#0"},
				"south": {"uv": [7.5, 4.875, 9.5, 5], "texture": "#0"},
				"west": {"uv": [7.625, 1.5, 8.75, 1.625], "texture": "#0"},
				"up": {"uv": [7.5, 6.5, 5.5, 5.375], "texture": "#0"},
				"down": {"uv": [6, 1.75, 4, 2.875], "texture": "#0"}
			}
		},
		{
			"from": [0, 11, 14],
			"to": [1, 25, 21],
			"rotation": {"angle": 0, "axis": "y", "origin": [8, 15.25, 12.25]},
			"faces": {
				"north": {"uv": [6.75, 7.5, 6.875, 9.25], "texture": "#0"},
				"east": {"uv": [4.875, 6.625, 5.75, 8.375], "texture": "#0"},
				"south": {"uv": [6.875, 7.5, 7, 9.25], "texture": "#0"},
				"west": {"uv": [5.75, 6.625, 6.625, 8.375], "texture": "#0"},
				"up": {"uv": [0.875, 8.75, 0.75, 7.875], "texture": "#0"},
				"down": {"uv": [1, 7.875, 0.875, 8.75], "texture": "#0"}
			}
		},
		{
			"from": [1, 11, 14.5],
			"to": [15, 25, 14.5],
			"rotation": {"angle": 0, "axis": "y", "origin": [8, 15.25, 12.25]},
			"faces": {
				"north": {"uv": [2, 4.125, 3.75, 5.875], "texture": "#0"},
				"east": {"uv": [0, 0, 0, 1.75], "texture": "#0"},
				"south": {"uv": [2, 4.125, 3.75, 5.875], "texture": "#0"},
				"west": {"uv": [0, 0, 0, 1.75], "texture": "#0"},
				"up": {"uv": [1.75, 0, 0, 0], "texture": "#0"},
				"down": {"uv": [1.75, 0, 0, 0], "texture": "#0"}
			}
		},
		{
			"from": [0.25, 12, 15.75],
			"to": [14.25, 15, 15.75],
			"rotation": {"angle": 0, "axis": "y", "origin": [8, 12.5, 14.75]},
			"faces": {
				"north": {"uv": [6, 1.75, 7.75, 2.125], "texture": "#0"},
				"east": {"uv": [0, 0, 0, 0.375], "texture": "#0"},
				"south": {"uv": [6, 2.125, 7.75, 2.5], "texture": "#0"},
				"west": {"uv": [0, 0, 0, 0.375], "texture": "#0"},
				"up": {"uv": [1.75, 0, 0, 0], "texture": "#0"},
				"down": {"uv": [1.75, 0, 0, 0], "texture": "#0"}
			}
		},
		{
			"from": [5, 10.97711, 15.44708],
			"to": [11, 12.97711, 21.69708],
			"rotation": {"angle": -22.5, "axis": "x", "origin": [8, 15.25, 12.25]},
			"faces": {
				"north": {"uv": [7.5, 5.5, 8.25, 5.75], "texture": "#0"},
				"east": {"uv": [8.3125, 5.25, 7.5, 5.5], "texture": "#0"},
				"south": {"uv": [7.5, 5.75, 8.25, 6], "texture": "#0"},
				"west": {"uv": [7.5, 5.25, 8.3125, 5.5], "texture": "#0"},
				"up": {"uv": [7.375, 7.4375, 6.625, 6.625], "texture": "#0"},
				"down": {"uv": [7.625, 0, 6.875, 0.8125], "texture": "#0"}
			}
		},
		{
			"from": [5, 16, 16],
			"to": [11, 21, 22],
			"rotation": {"angle": 0, "axis": "y", "origin": [8, 15.25, 12.25]},
			"faces": {
				"north": {"uv": [2.75, 7, 3.5, 7.625], "texture": "#0"},
				"east": {"uv": [8.125, 6.625, 7.375, 7.25], "texture": "#0"},
				"south": {"uv": [1.5, 7.25, 2.25, 7.875], "texture": "#0"},
				"west": {"uv": [7.375, 6.625, 8.125, 7.25], "texture": "#0"},
				"up": {"uv": [7.625, 1.625, 6.875, 0.875], "texture": "#0"},
				"down": {"uv": [0.75, 7, 0, 7.75], "texture": "#0"}
			}
		},
		{
			"from": [6.71122, 19.04065, 16.5],
			"to": [9.71122, 24.29065, 17.5],
			"rotation": {"angle": -22.5, "axis": "z", "origin": [8, 15.25, 12.25]},
			"faces": {
				"north": {"uv": [5.25, 5.875, 4.875, 6.5625], "texture": "#0"},
				"east": {"uv": [5.5, 5.875, 5.375, 6.5625], "texture": "#0"},
				"south": {"uv": [7.5, 4, 7.875, 4.6875], "texture": "#0"},
				"west": {"uv": [1.125, 7.875, 1.25, 8.5625], "texture": "#0"},
				"up": {"uv": [8.375, 1.5, 8, 1.375], "texture": "#0"},
				"down": {"uv": [2, 8, 1.625, 8.125], "texture": "#0"}
			}
		},
		{
			"from": [6.28878, 19.04065, 16.5],
			"to": [9.28878, 24.29065, 17.5],
			"rotation": {"angle": 22.5, "axis": "z", "origin": [8, 15.25, 12.25]},
			"faces": {
				"north": {"uv": [4.875, 5.875, 5.25, 6.5625], "texture": "#0"},
				"east": {"uv": [5.25, 5.875, 5.375, 6.5625], "texture": "#0"},
				"south": {"uv": [2.25, 7.25, 2.625, 7.9375], "texture": "#0"},
				"west": {"uv": [5.375, 5.875, 5.5, 6.5625], "texture": "#0"},
				"up": {"uv": [1.625, 8.125, 1.25, 8], "texture": "#0"},
				"down": {"uv": [8.375, 1.25, 8, 1.375], "texture": "#0"}
			}
		}
	],
	"gui_light": "front",
	"display": {
		"thirdperson_righthand": {
			"translation": [0, 1.75, 0],
			"scale": [0.24, 0.24, 0.24]
		},
		"thirdperson_lefthand": {
			"translation": [0, 1.75, 0],
			"scale": [0.24, 0.24, 0.24]
		},
		"firstperson_righthand": {
			"rotation": [-180, -5, -180],
			"translation": [0, 2.5, -0.75],
			"scale": [0.2793, 0.2793, 0.2793]
		},
		"firstperson_lefthand": {
			"rotation": [-180, -5, -180],
			"translation": [0, 2.5, -0.75],
			"scale": [0.2793, 0.2793, 0.2793]
		},
		"ground": {
			"scale": [0.22, 0.22, 0.22]
		},
		"gui": {
			"rotation": [30, 145, 0],
			"translation": [-0.75, -2.25, 0],
			"scale": [0.4, 0.4, 0.4]
		},
		"head": {
			"rotation": [0, -180, 0],
			"translation": [0, -30.5, 0],
			"scale": [1.6, 1.6, 1.6]
		},
		"fixed": {
			"rotation": [-90, 0, 0],
			"translation": [0, 0, -16],
			"scale": [2, 2, 2]
		}
	},
	"groups": [
		0,
		1,
		2,
		3,
		4,
		5,
		6,
		7,
		8,
		{
			"name": "group",
			"origin": [0, 0, 0],
			"color": 0,
			"children": [9, 10, 11, 12, 13]
		},
		14,
		15,
		{
			"name": "group",
			"origin": [8, 15.25, 12.25],
			"color": 0,
			"children": [16, 17, 18, 19]
		}
	]
}