{"textures":{"0":"modelengine:entity/flying_dutchman"},"elements":[{"from":[-5.714287,1.9999995,8.0],"to":[21.714287,8.0,8.0],"rotation":{"angle":0.0,"axis":"y","origin":[2.4285712,-33.14286,5.8571424]},"faces":{"east":{"uv":[0.0,0.0,0.0,0.4375],"rotation":0,"texture":"#0","tintindex":0},"south":{"uv":[4.875,2.125,2.875,2.5625],"rotation":0,"texture":"#0","tintindex":0},"north":{"uv":[2.875,2.125,4.875,2.5625],"rotation":0,"texture":"#0","tintindex":0},"west":{"uv":[0.0,0.0,0.0,0.4375],"rotation":0,"texture":"#0","tintindex":0},"up":{"uv":[2.0,0.0,0.0,0.0],"rotation":0,"texture":"#0","tintindex":0},"down":{"uv":[2.0,0.0,0.0,0.0],"rotation":0,"texture":"#0","tintindex":0}}}],"display":{"head":{"translation":[0.0,-6.4,0.0],"scale":[4.0,4.0,4.0]}}}