{"textures":{"0":"modelengine:entity/pohaku3"},"elements":[{"from":[0.03805542,0.5627222,10.116673],"to":[5.180913,9.70558,15.830959],"rotation":{"angle":22.5,"axis":"x","origin":[9.180913,22.277008,17.83096]},"faces":{"east":{"uv":[9.34375,9.0,9.65625,9.5],"rotation":0,"texture":"#0","tintindex":0},"south":{"uv":[9.5,8.40625,9.78125,8.90625],"rotation":0,"texture":"#0","tintindex":0},"north":{"uv":[9.46875,7.90625,9.75,8.40625],"rotation":0,"texture":"#0","tintindex":0},"west":{"uv":[1.25,9.375,1.5625,9.875],"rotation":0,"texture":"#0","tintindex":0},"up":{"uv":[10.03125,3.5,9.75,3.1875],"rotation":0,"texture":"#0","tintindex":0},"down":{"uv":[6.03125,9.75,5.75,10.0625],"rotation":0,"texture":"#0","tintindex":0}}},{"from":[10.980972,13.614653,5.893011],"to":[16.123829,16.471794,5.893011],"rotation":{"angle":0.0,"axis":"y","origin":[13.552401,32.75751,-0.39270306]},"faces":{"east":{"uv":[0.5,3.65625,0.5,3.78125],"rotation":0,"texture":"#0","tintindex":0},"south":{"uv":[0.5,3.84375,0.78125,4.0],"rotation":0,"texture":"#0","tintindex":0},"north":{"uv":[0.78125,3.84375,0.5,4.0],"rotation":0,"texture":"#0","tintindex":0},"west":{"uv":[0.5,3.65625,0.5,3.78125],"rotation":0,"texture":"#0","tintindex":0},"up":{"uv":[0.5,3.65625,0.78125,3.65625],"rotation":0,"texture":"#0","tintindex":0},"down":{"uv":[0.5,3.65625,0.78125,3.65625],"rotation":0,"texture":"#0","tintindex":0}}},{"from":[1.266686,1.7055793,12.973817],"to":[14.409544,9.70558,20.40239],"rotation":{"angle":22.5,"axis":"x","origin":[6.980972,22.277008,17.83096]},"faces":{"east":{"uv":[9.21875,1.6875,9.625,2.125],"rotation":0,"texture":"#0","tintindex":0},"south":{"uv":[8.09375,0.875,8.8125,1.3125],"rotation":0,"texture":"#0","tintindex":0},"north":{"uv":[8.09375,0.4375,8.8125,0.875],"rotation":0,"texture":"#0","tintindex":0},"west":{"uv":[9.21875,2.125,9.625,2.5625],"rotation":0,"texture":"#0","tintindex":0},"up":{"uv":[2.71875,8.625,2.0,8.21875],"rotation":0,"texture":"#0","tintindex":0},"down":{"uv":[1.09375,8.25,0.375,8.65625],"rotation":0,"texture":"#0","tintindex":0}}},{"from":[10.980972,0.5627222,10.116673],"to":[16.123829,9.70558,15.830959],"rotation":{"angle":22.5,"axis":"x","origin":[6.980972,22.277008,17.83096]},"faces":{"east":{"uv":[7.59375,9.375,7.90625,9.875],"rotation":0,"texture":"#0","tintindex":0},"south":{"uv":[9.53125,3.5625,9.8125,4.0625],"rotation":0,"texture":"#0","tintindex":0},"north":{"uv":[9.34375,9.5,9.625,10.0],"rotation":0,"texture":"#0","tintindex":0},"west":{"uv":[7.90625,9.375,8.21875,9.875],"rotation":0,"texture":"#0","tintindex":0},"up":{"uv":[6.3125,10.0625,6.03125,9.75],"rotation":0,"texture":"#0","tintindex":0},"down":{"uv":[7.375,9.75,7.09375,10.0625],"rotation":0,"texture":"#0","tintindex":0}}}],"display":{"head":{"translation":[0.0,-6.4,0.0],"scale":[4.0,4.0,4.0]}}}