{"textures":{"0":"modelengine:entity/christmascrate"},"elements":[{"from":[6.0,4.609524,6.0],"to":[10.0,6.895238,10.0],"rotation":{"angle":0.0,"axis":"y","origin":[-4.8571434,4.609524,6.5714283]},"faces":{"east":{"uv":[14.875,3.875,15.75,4.375],"rotation":0,"texture":"#0","tintindex":0},"south":{"uv":[14.875,3.875,15.75,4.375],"rotation":0,"texture":"#0","tintindex":0},"north":{"uv":[14.875,3.875,15.75,4.375],"rotation":0,"texture":"#0","tintindex":0},"west":{"uv":[14.875,3.875,15.75,4.375],"rotation":0,"texture":"#0","tintindex":0},"up":{"uv":[15.0,15.0,14.125,14.125],"rotation":0,"texture":"#0","tintindex":0},"down":{"uv":[15.125,0.0,14.25,0.875],"rotation":0,"texture":"#0","tintindex":0}}},{"from":[5.714286,6.838095,5.714286],"to":[10.285714,9.12381,10.285714],"rotation":{"angle":0.0,"axis":"y","origin":[-4.8571434,4.609524,6.5714283]},"faces":{"east":{"uv":[14.625,11.0,15.625,11.5],"rotation":0,"texture":"#0","tintindex":0},"south":{"uv":[14.625,11.0,15.625,11.5],"rotation":0,"texture":"#0","tintindex":0},"north":{"uv":[14.625,11.0,15.625,11.5],"rotation":0,"texture":"#0","tintindex":0},"west":{"uv":[14.625,11.0,15.625,11.5],"rotation":0,"texture":"#0","tintindex":0},"up":{"uv":[14.125,14.25,13.125,13.25],"rotation":0,"texture":"#0","tintindex":0},"down":{"uv":[3.375,13.375,2.375,14.375],"rotation":0,"texture":"#0","tintindex":0}}},{"from":[5.714286,9.12381,8.0],"to":[10.285714,11.409524,8.0],"rotation":{"angle":0.0,"axis":"y","origin":[-4.8571434,4.609524,6.5714283]},"faces":{"east":{"uv":[0.0,0.0,0.0,0.5],"rotation":0,"texture":"#0","tintindex":0},"south":{"uv":[8.5,15.5,7.5,16.0],"rotation":0,"texture":"#0","tintindex":0},"north":{"uv":[7.5,15.5,8.5,16.0],"rotation":0,"texture":"#0","tintindex":0},"west":{"uv":[0.0,0.0,0.0,0.5],"rotation":0,"texture":"#0","tintindex":0},"up":{"uv":[1.0,0.0,0.0,0.0],"rotation":0,"texture":"#0","tintindex":0},"down":{"uv":[1.0,0.0,0.0,0.0],"rotation":0,"texture":"#0","tintindex":0}}}],"display":{"head":{"translation":[0.0,-6.4,0.0],"scale":[4.0,4.0,4.0]}}}