{"textures":{"0":"modelengine:entity/mso_narwhal"},"elements":[{"from":[7.428571,7.428571,-6.4285717],"to":[8.571428,8.571428,3.2857141],"rotation":{"angle":0.0,"axis":"y","origin":[7.428571,4.5714283,18.714287]},"faces":{"east":{"uv":[6.5,0.625,8.625,0.875],"rotation":0,"texture":"#0","tintindex":0},"south":{"uv":[3.0,6.875,3.25,7.125],"rotation":0,"texture":"#0","tintindex":0},"north":{"uv":[3.125,6.625,3.375,6.875],"rotation":0,"texture":"#0","tintindex":0},"west":{"uv":[6.5,0.875,8.625,1.125],"rotation":0,"texture":"#0","tintindex":0},"up":{"uv":[3.75,7.875,3.5,5.75],"rotation":0,"texture":"#0","tintindex":0},"down":{"uv":[4.0,6.5,3.75,8.625],"rotation":0,"texture":"#0","tintindex":0}}},{"from":[5.142857,5.142857,3.2857141],"to":[10.857143,10.857143,9.0],"rotation":{"angle":0.0,"axis":"y","origin":[5.142857,4.5714283,18.714287]},"faces":{"east":{"uv":[5.0,2.75,6.25,4.0],"rotation":0,"texture":"#0","tintindex":0},"south":{"uv":[5.0,4.0,6.25,5.25],"rotation":0,"texture":"#0","tintindex":0},"north":{"uv":[5.0,1.5,6.25,2.75],"rotation":0,"texture":"#0","tintindex":0},"west":{"uv":[5.25,0.0,6.5,1.25],"rotation":0,"texture":"#0","tintindex":0},"up":{"uv":[5.0,6.5,3.75,5.25],"rotation":0,"texture":"#0","tintindex":0},"down":{"uv":[6.25,5.25,5.0,6.5],"rotation":0,"texture":"#0","tintindex":0}}}],"display":{"head":{"translation":[0.0,-6.4,0.0],"scale":[4.0,4.0,4.0]}}}